docs/conf.py
graph_learn/__init__.py
graph_learn/evaluation.py
graph_learn/lgmrf.py
graph_learn/operators.py
graph_learn/smooth_learning.py
graph_learn/clustering/__init__.py
graph_learn/clustering/glmm.py
graph_learn/clustering/kgraphs.py
graph_learn/clustering/utils.py
graph_learn/dictionary/__init__.py
graph_learn/dictionary/base_model.py
graph_learn/dictionary/exact_model.py
graph_learn/dictionary/fixed_models.py
graph_learn/dictionary/log_model.py
graph_learn/dictionary/spectral_model.py
graph_learn/dictionary/utils.py
graph_learn/sampling/__init__.py
graph_learn/sampling/graphs.py
graph_learn/sampling/signals.py
graph_learn/temporal/__init__.py
graph_learn/temporal/graph_factor.py
graph_learn/temporal/smooth.py
tests/test_clustering.py
tests/test_models.py
tests/test_operators.py
graph_structure_learning-0.1.3.dist-info/LICENSE
graph_structure_learning-0.1.3.dist-info/METADATA
graph_structure_learning-0.1.3.dist-info/WHEEL
graph_structure_learning-0.1.3.dist-info/top_level.txt
graph_structure_learning-0.1.3.dist-info/RECORD
