Metadata-Version: 2.1
Name: graph_structure_learning
Version: 0.1.3
Summary: Extracting graphs from signals on nodes
Author-email: William Cappelletti <william.cappelletti@epfl.ch>
License: BSD-3-Clause
Project-URL: Homepage, https://github.com/LTS4/graph-learning
Project-URL: Issues, https://github.com/LTS4/graph-learning/issues
Keywords: machine learning,graph,network,signal processing,clustering,time series
Classifier: Programming Language :: Python :: 3
Classifier: Development Status :: 3 - Alpha
Classifier: License :: OSI Approved :: BSD License
Classifier: Operating System :: OS Independent
Classifier: Natural Language :: English
Classifier: Topic :: Scientific/Engineering :: Artificial Intelligence
Requires-Python: >=3.10
License-File: LICENSE
Requires-Dist: numpy<=2.1
Requires-Dist: scikit-learn
Requires-Dist: tqdm
Requires-Dist: pandas
Provides-Extra: dev
Requires-Dist: pylint; extra == "dev"
Requires-Dist: pytest; extra == "dev"
Requires-Dist: black; extra == "dev"
Requires-Dist: isort; extra == "dev"
Provides-Extra: build
Requires-Dist: build; extra == "build"
Requires-Dist: twine; extra == "build"
